pyia/__init__.py
pyia/_version.py
pyia/_version.pyi
pyia/data.py
pyia/extinction.py
pyia/setup_package.py
pyia/data/readme.txt
pyia/data/table_u0_2D.txt
pyia/data/table_u0_g.txt
pyia/data/table_u0_g_col.txt
pyia-1.4.1.dist-info/METADATA
pyia-1.4.1.dist-info/WHEEL
pyia-1.4.1.dist-info/licenses/LICENSE
pyia-1.4.1.dist-info/RECORD
