Metadata-Version: 2.1
Name: pyia
Version: 1.4.1
Summary: A Python package for working with data from the Gaia mission
Project-URL: Homepage, https://github.com/adrn/pyia
Project-URL: Bug Tracker, https://github.com/adrn/pyia/issues
Project-URL: Discussions, https://github.com/adrn/pyia/discussions
Project-URL: Changelog, https://github.com/adrn/pyia/releases
Author-email: Adrian Price-Whelan <adrianmpw@gmail.com>
License: Copyright 2023 Adrian Price-Whelan
License-File: LICENSE
Classifier: Development Status :: 1 - Planning
Classifier: Intended Audience :: Developers
Classifier: Intended Audience :: Science/Research
Classifier: License :: OSI Approved :: MIT License
Classifier: Operating System :: OS Independent
Classifier: Programming Language :: Python
Classifier: Programming Language :: Python :: 3
Classifier: Programming Language :: Python :: 3 :: Only
Classifier: Programming Language :: Python :: 3.8
Classifier: Programming Language :: Python :: 3.9
Classifier: Programming Language :: Python :: 3.10
Classifier: Programming Language :: Python :: 3.11
Classifier: Programming Language :: Python :: 3.12
Classifier: Topic :: Scientific/Engineering
Classifier: Typing :: Typed
Requires-Python: >=3.8
Requires-Dist: astropy
Requires-Dist: numpy
Requires-Dist: pandas
Provides-Extra: docs
Requires-Dist: matplotlib; extra == 'docs'
Requires-Dist: pydata-sphinx-theme; extra == 'docs'
Requires-Dist: pyia[optional]; extra == 'docs'
Requires-Dist: sphinx-autodoc-typehints; extra == 'docs'
Requires-Dist: sphinx-automodapi; extra == 'docs'
Requires-Dist: sphinx-copybutton; extra == 'docs'
Requires-Dist: sphinx>=7.0; extra == 'docs'
Provides-Extra: optional
Requires-Dist: astroquery; extra == 'optional'
Requires-Dist: dustmaps; extra == 'optional'
Provides-Extra: test
Requires-Dist: pyia[optional]; extra == 'test'
Requires-Dist: pytest-astropy; extra == 'test'
Requires-Dist: pytest-cov>=3; extra == 'test'
Requires-Dist: pytest>=6; extra == 'test'
